huiguang/__init__.py
huiguang/huiguang_sou.py
huiguang-1.0.3.dist-info/METADATA
huiguang-1.0.3.dist-info/WHEEL
huiguang-1.0.3.dist-info/top_level.txt
huiguang-1.0.3.dist-info/RECORD
