Metadata-Version: 2.1
Name: huiguang
Version: 1.0.3
Summary: This software is some simple search
Home-page: https://gitee.com/tian-huiguang/tian-huiguang-homework
Author: tianmou
Author-email: 1039211901@qq.com
